pix8.py
pix8-0.0.4.dist-info/licenses/LICENSE.txt
pix8-0.0.4.dist-info/METADATA
pix8-0.0.4.dist-info/WHEEL
pix8-0.0.4.dist-info/entry_points.txt
pix8-0.0.4.dist-info/top_level.txt
pix8-0.0.4.dist-info/RECORD
