Metadata-Version: 2.4
Name: pix8
Version: 0.0.4
Summary: Tiny fantasy console
License-File: LICENSE.txt
Requires-Dist: pygame-ce
Dynamic: license-file
